[
    {
        "name": " ",
        "safeAddr": "",
        "numberOfSigners": 2,
        "numberOfUsers": 3,
        "creator": "0x...",
        "deployed": false,
        "users": [
            {
                "email": "aa@aaa.fr",
                "address": "0x00",
                "joined": false
            }
        ]
    },
    {
        "name": "nameOfTheSafe",
        "safeAddr": "",
        "numberOfSigners": "2",
        "numberOfUsers": 2,
        "deployed": false,
        "users": [
            {
                "email": "azeaze",
                "address": "",
                "joined": false
            },
            {
                "email": "azeaze",
                "address": "",
                "joined": false
            }
        ]
    },
    {
        "name": "nameOfTheSafe",
        "safeAddr": "",
        "numberOfSigners": "2",
        "numberOfUsers": 2,
        "deployed": false,
        "users": [
            {
                "email": "azeaze",
                "address": "",
                "joined": false
            },
            {
                "email": "azeaze",
                "address": "",
                "joined": false
            }
        ]
    },
    {
        "name": "nameOfTheSafe",
        "safeAddr": "",
        "numberOfSigners": 1,
        "numberOfUsers": 2,
        "creator": "0x770c84b458cD19BAfA5F59dE0a3Bf10Aa95BB008",
        "deployed": false,
        "users": [
            {
                "email": "aze",
                "address": "",
                "joined": false
            },
            {
                "email": "aze",
                "address": "",
                "joined": false
            }
        ]
    },
    {
        "name": "nameOfTheSafe",
        "safeAddr": "",
        "numberOfSigners": "2",
        "numberOfUsers": 3,
        "creator": "0x770c84b458cD19BAfA5F59dE0a3Bf10Aa95BB008",
        "deployed": false,
        "users": [
            {
                "email": "aze",
                "address": "",
                "joined": false
            },
            {
                "email": "aze",
                "address": "",
                "joined": false
            },
            {
                "email": "florent@gmail.cm",
                "address": "",
                "joined": false
            }
        ]
    }
]